pycldf/__init__.py
pycldf/__main__.py
pycldf/cli_util.py
pycldf/dataset.py
pycldf/db.py
pycldf/media.py
pycldf/orm.py
pycldf/sources.py
pycldf/terms.py
pycldf/terms.rdf
pycldf/trees.py
pycldf/util.py
pycldf/validators.py
pycldf/commands/__init__.py
pycldf/commands/catmedia.py
pycldf/commands/check.py
pycldf/commands/createdb.py
pycldf/commands/downloadmedia.py
pycldf/commands/dumpdb.py
pycldf/commands/markdown.py
pycldf/commands/splitmedia.py
pycldf/commands/stats.py
pycldf/commands/validate.py
pycldf/components/BorrowingTable-metadata.json
pycldf/components/CodeTable-metadata.json
pycldf/components/CognateTable-metadata.json
pycldf/components/CognatesetTable-metadata.json
pycldf/components/ContributionTable-metadata.json
pycldf/components/EntryTable-metadata.json
pycldf/components/ExampleTable-metadata.json
pycldf/components/FormTable-metadata.json
pycldf/components/FunctionalEquivalentTable-metadata.json
pycldf/components/FunctionalEquivalentsetTable-metadata.json
pycldf/components/LanguageTable-metadata.json
pycldf/components/MediaTable-metadata.json
pycldf/components/ParameterNetwork-metadata.json
pycldf/components/ParameterTable-metadata.json
pycldf/components/SenseTable-metadata.json
pycldf/components/TreeTable-metadata.json
pycldf/components/ValueTable-metadata.json
pycldf/ext/__init__.py
pycldf/ext/discovery.py
pycldf/ext/markdown.py
pycldf/ext/sql.py
pycldf/modules/Dictionary-metadata.json
pycldf/modules/Generic-metadata.json
pycldf/modules/ParallelText-metadata.json
pycldf/modules/StructureDataset-metadata.json
pycldf/modules/TextCorpus-metadata.json
pycldf/modules/Wordlist-metadata.json
pycldf-1.43.0.dist-info/LICENSE
pycldf-1.43.0.dist-info/METADATA
pycldf-1.43.0.dist-info/WHEEL
pycldf-1.43.0.dist-info/entry_points.txt
pycldf-1.43.0.dist-info/top_level.txt
pycldf-1.43.0.dist-info/RECORD
