Metadata-Version: 2.1
Name: pycldf
Version: 1.43.0
Summary: A python library to read and write CLDF datasets
Home-page: https://github.com/cldf/pycldf
Author: Robert Forkel
Author-email: robert_forkel@eva.mpg.de
License: Apache 2.0
Project-URL: Bug Tracker, https://github.com/cldf/pycldf/issues
Keywords: linguistics
Platform: any
Classifier: Development Status :: 5 - Production/Stable
Classifier: Intended Audience :: Developers
Classifier: Intended Audience :: Science/Research
Classifier: Natural Language :: English
Classifier: Operating System :: OS Independent
Classifier: Programming Language :: Python :: 3
Classifier: Programming Language :: Python :: 3.8
Classifier: Programming Language :: Python :: 3.9
Classifier: Programming Language :: Python :: 3.10
Classifier: Programming Language :: Python :: 3.11
Classifier: Programming Language :: Python :: 3.12
Classifier: Programming Language :: Python :: 3.13
Classifier: Programming Language :: Python :: Implementation :: CPython
Classifier: Programming Language :: Python :: Implementation :: PyPy
Classifier: License :: OSI Approved :: Apache Software License
Requires-Python: >=3.8
License-File: LICENSE
Requires-Dist: csvw>=1.10
Requires-Dist: clldutils>=3.9
Requires-Dist: uritemplate>=3.0
Requires-Dist: python-dateutil
Requires-Dist: simplepybtex
Requires-Dist: newick
Requires-Dist: commonnexus>=1.2.0
Requires-Dist: python-frontmatter
Requires-Dist: termcolor
Requires-Dist: PyYAML
Requires-Dist: jmespath
Provides-Extra: catalogs
Requires-Dist: cldfcatalog; extra == "catalogs"
Requires-Dist: pyglottolog; extra == "catalogs"
Requires-Dist: pyconcepticon; extra == "catalogs"
Provides-Extra: dev
Requires-Dist: tox; extra == "dev"
Requires-Dist: flake8; extra == "dev"
Requires-Dist: wheel>=0.36; extra == "dev"
Requires-Dist: twine; extra == "dev"
Provides-Extra: test
Requires-Dist: packaging; extra == "test"
Requires-Dist: cldfcatalog; extra == "test"
Requires-Dist: pyglottolog; extra == "test"
Requires-Dist: pyconcepticon; extra == "test"
Requires-Dist: pytest>=5; extra == "test"
Requires-Dist: pytest-mock; extra == "test"
Requires-Dist: requests-mock; extra == "test"
Requires-Dist: pytest-cov; extra == "test"
Requires-Dist: coverage>=4.2; extra == "test"
Provides-Extra: docs
Requires-Dist: sphinx<7; extra == "docs"
Requires-Dist: sphinx-autodoc-typehints; extra == "docs"
Requires-Dist: sphinx-rtd-theme; extra == "docs"
